3_module_chk/cnt.v
// DESCRIPTION: Verilator: Verilog example module
//
// This file ONLY is placed under the Creative Commons Public Domain, for
// any use, without warranty, 2017 by Wilson Snyder.
// SPDX-License-Identifier: CC0-1.0

// See also the EXAMPLE section in the verilator manpage/document.

`timescale 1ns/1ps

module cnt(
	input clk,
	input rstn,
	output reg [15:0] out,
	output chk_3
);

	chk_3_multiple u0(
			.clk(clk),
			.chk_num(out),
			.chk_out(chk_3)
	);

	always @(posedge clk, negedge rstn)
	begin
		if(!rstn)
		begin
			out<=0;
		end
		else
		begin
			if(out<300)
			begin
				out<=out+1;
			end
			else
			begin
				out<=0;
			end		
		end
	end
endmodule

module chk_3_multiple(
		input clk,
		input [15:0] chk_num,
		output chk_out
		);

assign chk_out = (chk_num%3 == 0);

endmodule

3_module_chk/top.vcd
$version Generated by VerilatedVcd $end
$date Thu May 28 17:16:30 2020
 $end
$timescale   1ps $end

 $scope module TOP $end
  $var wire  1 & chk_3 $end
  $var wire  1 # clk $end
  $var wire 16 % out [15:0] $end
  $var wire  1 $ rstn $end
  $scope module cnt $end
   $var wire  1 & chk_3 $end
   $var wire  1 # clk $end
   $var wire 16 % out [15:0] $end
   $var wire  1 $ rstn $end
   $scope module u0 $end
    $var wire 16 % chk_num [15:0] $end
    $var wire  1 & chk_out $end
    $var wire  1 # clk $end
   $upscope $end
  $upscope $end
 $upscope $end
$enddefinitions $end


#0
1#
1$
b0000000000000001 %
0&
#1
0#
#2
1#
b0000000000000010 %
#3
0#
#4
1#
b0000000000000011 %
#5
0#
#6
1#
b0000000000000100 %
#7
0#
#8
1#
b0000000000000101 %
#9
0#
#10
1#
b0000000000000110 %
#11
0#
#12
1#
b0000000000000111 %
#13
0#
#14
1#
b0000000000001000 %
#15
0#
#16
1#
b0000000000001001 %
#17
0#
#18
1#
b0000000000001010 %
#19
0#
#20
1#
b0000000000001011 %
#21
0#
#22
1#
b0000000000001100 %
#23
0#
#24
1#
b0000000000001101 %
#25
0#
#26
1#
b0000000000001110 %
#27
0#
#28
1#
b0000000000001111 %
#29
0#
#30
1#
b0000000000010000 %
#31
0#
#32
1#
b0000000000010001 %
#33
0#
#34
1#
b0000000000010010 %
#35
0#
#36
1#
b0000000000010011 %
#37
0#
#38
1#
b0000000000010100 %
#39
0#
#40
1#
b0000000000010101 %
#41
0#
#42
1#
b0000000000010110 %
#43
0#
#44
1#
b0000000000010111 %
#45
0#
#46
1#
b0000000000011000 %
#47
0#
#48
1#
b0000000000011001 %
#49
0#
#50
1#
b0000000000011010 %
#51
0#
#52
1#
b0000000000011011 %
#53
0#
#54
1#
b0000000000011100 %
#55
0#
#56
1#
b0000000000011101 %
#57
0#
#58
1#
b0000000000011110 %
#59
0#
#60
1#
b0000000000011111 %
#61
0#
#62
1#
b0000000000100000 %
#63
0#
#64
1#
b0000000000100001 %
#65
0#
#66
1#
b0000000000100010 %
#67
0#
#68
1#
b0000000000100011 %
#69
0#
#70
1#
b0000000000100100 %
#71
0#
#72
1#
b0000000000100101 %
#73
0#
#74
1#
b0000000000100110 %
#75
0#
#76
1#
b0000000000100111 %
#77
0#
#78
1#
b0000000000101000 %
#79
0#
#80
1#
b0000000000101001 %
#81
0#
#82
1#
b0000000000101010 %
#83
0#
#84
1#
b0000000000101011 %
#85
0#
#86
1#
b0000000000101100 %
#87
0#
#88
1#
b0000000000101101 %
#89
0#
#90
1#
b0000000000101110 %
#91
0#
#92
1#
b0000000000101111 %
#93
0#
#94
1#
b0000000000110000 %
#95
0#
#96
1#
b0000000000110001 %
#97
0#
#98
1#
b0000000000110010 %
#99
0#
#100
1#
b0000000000110011 %
#101
0#
#102
1#
b0000000000110100 %
#103
0#
#104
1#
b0000000000110101 %
#105
0#
#106
1#
b0000000000110110 %
#107
0#
#108
1#
b0000000000110111 %
#109
0#
#110
1#
b0000000000111000 %
#111
0#
#112
1#
b0000000000111001 %
#113
0#
#114
1#
b0000000000111010 %
#115
0#
#116
1#
b0000000000111011 %
#117
0#
#118
1#
b0000000000111100 %
#119
0#
#120
1#
b0000000000111101 %
#121
0#
#122
1#
b0000000000111110 %
#123
0#
#124
1#
b0000000000111111 %
#125
0#
#126
1#
b0000000001000000 %
#127
0#
#128
1#
b0000000001000001 %
#129
0#
#130
1#
b0000000001000010 %
#131
0#
#132
1#
b0000000001000011 %
#133
0#
#134
1#
b0000000001000100 %
#135
0#
#136
1#
b0000000001000101 %
#137
0#
#138
1#
b0000000001000110 %
#139
0#
#140
1#
b0000000001000111 %
#141
0#
#142
1#
b0000000001001000 %
#143
0#
#144
1#
b0000000001001001 %
#145
0#
#146
1#
b0000000001001010 %
#147
0#
#148
1#
b0000000001001011 %
#149
0#
#150
1#
b0000000001001100 %
#151
0#
#152
1#
b0000000001001101 %
#153
0#
#154
1#
b0000000001001110 %
#155
0#
#156
1#
b0000000001001111 %
#157
0#
#158
1#
b0000000001010000 %
#159
0#
#160
1#
b0000000001010001 %
#161
0#
#162
1#
b0000000001010010 %
#163
0#
#164
1#
b0000000001010011 %
#165
0#
#166
1#
b0000000001010100 %
#167
0#
#168
1#
b0000000001010101 %
#169
0#
#170
1#
b0000000001010110 %
#171
0#
#172
1#
b0000000001010111 %
#173
0#
#174
1#
b0000000001011000 %
#175
0#
#176
1#
b0000000001011001 %
#177
0#
#178
1#
b0000000001011010 %
#179
0#
#180
1#
b0000000001011011 %
#181
0#
#182
1#
b0000000001011100 %
#183
0#
#184
1#
b0000000001011101 %
#185
0#
#186
1#
b0000000001011110 %
#187
0#
#188
1#
b0000000001011111 %
#189
0#
#190
1#
b0000000001100000 %
#191
0#
#192
1#
b0000000001100001 %
#193
0#
#194
1#
b0000000001100010 %
#195
0#
#196
1#
b0000000001100011 %
#197
0#
#198
1#
b0000000001100100 %
#199
0#
#200
1#
b0000000001100101 %
#201
0#
#202
1#
b0000000001100110 %
#203
0#
#204
1#
b0000000001100111 %
#205
0#
#206
1#
b0000000001101000 %
#207
0#
#208
1#
b0000000001101001 %
#209
0#
#210
1#
b0000000001101010 %
#211
0#
#212
1#
b0000000001101011 %
#213
0#
#214
1#
b0000000001101100 %
#215
0#
#216
1#
b0000000001101101 %
#217
0#
#218
1#
b0000000001101110 %
#219
0#
#220
1#
b0000000001101111 %
#221
0#
#222
1#
b0000000001110000 %
#223
0#
#224
1#
b0000000001110001 %
#225
0#
#226
1#
b0000000001110010 %
#227
0#
#228
1#
b0000000001110011 %
#229
0#
#230
1#
b0000000001110100 %
#231
0#
#232
1#
b0000000001110101 %
#233
0#
#234
1#
b0000000001110110 %
#235
0#
#236
1#
b0000000001110111 %
#237
0#
#238
1#
b0000000001111000 %
#239
0#
#240
1#
b0000000001111001 %
#241
0#
#242
1#
b0000000001111010 %
#243
0#
#244
1#
b0000000001111011 %
#245
0#
#246
1#
b0000000001111100 %
#247
0#
#248
1#
b0000000001111101 %
#249
0#
#250
1#
b0000000001111110 %
#251
0#
#252
1#
b0000000001111111 %
#253
0#
#254
1#
b0000000010000000 %
#255
0#
#256
1#
b0000000010000001 %
#257
0#
#258
1#
b0000000010000010 %
#259
0#
#260
1#
b0000000010000011 %
#261
0#
#262
1#
b0000000010000100 %
#263
0#
#264
1#
b0000000010000101 %
#265
0#
#266
1#
b0000000010000110 %
#267
0#
#268
1#
b0000000010000111 %
#269
0#
#270
1#
b0000000010001000 %
#271
0#
#272
1#
b0000000010001001 %
#273
0#
#274
1#
b0000000010001010 %
#275
0#
#276
1#
b0000000010001011 %
#277
0#
#278
1#
b0000000010001100 %
#279
0#
#280
1#
b0000000010001101 %
#281
0#
#282
1#
b0000000010001110 %
#283
0#
#284
1#
b0000000010001111 %
#285
0#
#286
1#
b0000000010010000 %
#287
0#
#288
1#
b0000000010010001 %
#289
0#
#290
1#
b0000000010010010 %
#291
0#
#292
1#
b0000000010010011 %
#293
0#
#294
1#
b0000000010010100 %
#295
0#
#296
1#
b0000000010010101 %
#297
0#
#298
1#
b0000000010010110 %
#299
0#
#300
1#
b0000000010010111 %
#301
0#
#302
1#
b0000000010011000 %
#303
0#
#304
1#
b0000000010011001 %
#305
0#
#306
1#
b0000000010011010 %
#307
0#
#308
1#
b0000000010011011 %
#309
0#
#310
1#
b0000000010011100 %
#311
0#
#312
1#
b0000000010011101 %
#313
0#
#314
1#
b0000000010011110 %
#315
0#
#316
1#
b0000000010011111 %
#317
0#
#318
1#
b0000000010100000 %
#319
0#
#320
1#
b0000000010100001 %
#321
0#
#322
1#
b0000000010100010 %
#323
0#
#324
1#
b0000000010100011 %
#325
0#
#326
1#
b0000000010100100 %
#327
0#
#328
1#
b0000000010100101 %
#329
0#
#330
1#
b0000000010100110 %
#331
0#
#332
1#
b0000000010100111 %
#333
0#
#334
1#
b0000000010101000 %
#335
0#
#336
1#
b0000000010101001 %
#337
0#
#338
1#
b0000000010101010 %
#339
0#
#340
1#
b0000000010101011 %
#341
0#
#342
1#
b0000000010101100 %
#343
0#
#344
1#
b0000000010101101 %
#345
0#
#346
1#
b0000000010101110 %
#347
0#
#348
1#
b0000000010101111 %
#349
0#
#350
1#
b0000000010110000 %
#351
0#
#352
1#
b0000000010110001 %
#353
0#
#354
1#
b0000000010110010 %
#355
0#
#356
1#
b0000000010110011 %
#357
0#
#358
1#
b0000000010110100 %
#359
0#
#360
1#
b0000000010110101 %
#361
0#
#362
1#
b0000000010110110 %
#363
0#
#364
1#
b0000000010110111 %
#365
0#
#366
1#
b0000000010111000 %
#367
0#
#368
1#
b0000000010111001 %
#369
0#
#370
1#
b0000000010111010 %
#371
0#
#372
1#
b0000000010111011 %
#373
0#
#374
1#
b0000000010111100 %
#375
0#
#376
1#
b0000000010111101 %
#377
0#
#378
1#
b0000000010111110 %
#379
0#
#380
1#
b0000000010111111 %
#381
0#
#382
1#
b0000000011000000 %
#383
0#
#384
1#
b0000000011000001 %
#385
0#
#386
1#
b0000000011000010 %
#387
0#
#388
1#
b0000000011000011 %
#389
0#
#390
1#
b0000000011000100 %
#391
0#
#392
1#
b0000000011000101 %
#393
0#
#394
1#
b0000000011000110 %
#395
0#
#396
1#
b0000000011000111 %
#397
0#
#398
1#
b0000000011001000 %
#399
0#
#400
1#
b0000000011001001 %
#401
0#
#402
1#
b0000000011001010 %
#403
0#
#404
1#
b0000000011001011 %
#405
0#
#406
1#
b0000000011001100 %
#407
0#
#408
1#
b0000000011001101 %
#409
0#
#410
1#
b0000000011001110 %
#411
0#
#412
1#
b0000000011001111 %
#413
0#
#414
1#
b0000000011010000 %
#415
0#
#416
1#
b0000000011010001 %
#417
0#
#418
1#
b0000000011010010 %
#419
0#
#420
1#
b0000000011010011 %
#421
0#
#422
1#
b0000000011010100 %
#423
0#
#424
1#
b0000000011010101 %
#425
0#
#426
1#
b0000000011010110 %
#427
0#
#428
1#
b0000000011010111 %
#429
0#
#430
1#
b0000000011011000 %
#431
0#
#432
1#
b0000000011011001 %
#433
0#
#434
1#
b0000000011011010 %
#435
0#
#436
1#
b0000000011011011 %
#437
0#
#438
1#
b0000000011011100 %
#439
0#
#440
1#
b0000000011011101 %
#441
0#
#442
1#
b0000000011011110 %
#443
0#
#444
1#
b0000000011011111 %
#445
0#
#446
1#
b0000000011100000 %
#447
0#
#448
1#
b0000000011100001 %
#449
0#
#450
1#
b0000000011100010 %
#451
0#
#452
1#
b0000000011100011 %
#453
0#
#454
1#
b0000000011100100 %
#455
0#
#456
1#
b0000000011100101 %
#457
0#
#458
1#
b0000000011100110 %
#459
0#
#460
1#
b0000000011100111 %
#461
0#
#462
1#
b0000000011101000 %
#463
0#
#464
1#
b0000000011101001 %
#465
0#
#466
1#
b0000000011101010 %
#467
0#
#468
1#
b0000000011101011 %
#469
0#
#470
1#
b0000000011101100 %
#471
0#
#472
1#
b0000000011101101 %
#473
0#
#474
1#
b0000000011101110 %
#475
0#
#476
1#
b0000000011101111 %
#477
0#
#478
1#
b0000000011110000 %
#479
0#
#480
1#
b0000000011110001 %
#481
0#
#482
1#
b0000000011110010 %
#483
0#
#484
1#
b0000000011110011 %
#485
0#
#486
1#
b0000000011110100 %
#487
0#
#488
1#
b0000000011110101 %
#489
0#
#490
1#
b0000000011110110 %
#491
0#
#492
1#
b0000000011110111 %
#493
0#
#494
1#
b0000000011111000 %
#495
0#
#496
1#
b0000000011111001 %
#497
0#
#498
1#
b0000000011111010 %
#499
0#
#500
1#
b0000000011111011 %
#501
0#
#502
1#
b0000000011111100 %
#503
0#
#504
1#
b0000000011111101 %
#505
0#
#506
1#
b0000000011111110 %
#507
0#
#508
1#
b0000000011111111 %
#509
0#
#510
1#
b0000000100000000 %
#511
0#
#512
1#
b0000000100000001 %
#513
0#
#514
1#
b0000000100000010 %
#515
0#
#516
1#
b0000000100000011 %
#517
0#
#518
1#
b0000000100000100 %
#519
0#
#520
1#
b0000000100000101 %
#521
0#
#522
1#
b0000000100000110 %
#523
0#
#524
1#
b0000000100000111 %
#525
0#
#526
1#
b0000000100001000 %
#527
0#
#528
1#
b0000000100001001 %
#529
0#
#530
1#
b0000000100001010 %
#531
0#
#532
1#
b0000000100001011 %
#533
0#
#534
1#
b0000000100001100 %
#535
0#
#536
1#
b0000000100001101 %
#537
0#
#538
1#
b0000000100001110 %
#539
0#
#540
1#
b0000000100001111 %
#541
0#
#542
1#
b0000000100010000 %
#543
0#
#544
1#
b0000000100010001 %
#545
0#
#546
1#
b0000000100010010 %
#547
0#
#548
1#
b0000000100010011 %
#549
0#
#550
1#
b0000000100010100 %
#551
0#
#552
1#
b0000000100010101 %
#553
0#
#554
1#
b0000000100010110 %
#555
0#
#556
1#
b0000000100010111 %
#557
0#
#558
1#
b0000000100011000 %
#559
0#
#560
1#
b0000000100011001 %
#561
0#
#562
1#
b0000000100011010 %
#563
0#
#564
1#
b0000000100011011 %
#565
0#
#566
1#
b0000000100011100 %
#567
0#
#568
1#
b0000000100011101 %
#569
0#
#570
1#
b0000000100011110 %
#571
0#
#572
1#
b0000000100011111 %
#573
0#
#574
1#
b0000000100100000 %
#575
0#
#576
1#
b0000000100100001 %
#577
0#
#578
1#
b0000000100100010 %
#579
0#
#580
1#
b0000000100100011 %
#581
0#
#582
1#
b0000000100100100 %
#583
0#
#584
1#
b0000000100100101 %
#585
0#
#586
1#
b0000000100100110 %
#587
0#
#588
1#
b0000000100100111 %
#589
0#
#590
1#
b0000000100101000 %
#591
0#
#592
1#
b0000000100101001 %
#593
0#
#594
1#
b0000000100101010 %
#595
0#
#596
1#
b0000000100101011 %
#597
0#
#598
1#
b0000000100101100 %
